setup.py
rede/__init__.py
rede/rede.py
rede/rnp.py
rede/util.py
rede.egg-info/PKG-INFO
rede.egg-info/SOURCES.txt
rede.egg-info/dependency_links.txt
rede.egg-info/requires.txt
rede.egg-info/top_level.txt