Metadata-Version: 1.0
Name: rede
Version: 1.2
Summary: Funcionalidades para representacao da rede eletrica utilizando grafos com representacao no-profundidade
Home-page: UNKNOWN
Author: Lucas S Melo
Author-email: UNKNOWN
License: UNKNOWN
Platform: UNKNOWN
